quetz_theme/__init__.py
quetz_theme/_version.py
quetz_theme/labextension/package.json
quetz_theme/labextension/static/568.6ba9547c6360a2723636.js
quetz_theme/labextension/static/remoteEntry.b32b6c7ec2179a7bc5fc.js
quetz_theme/labextension/static/style.js
quetz_theme/labextension/static/third-party-licenses.json
quetz_theme/labextension/themes/quetz-theme/index.css
quetz_theme/labextension/themes/quetz-theme/index.js
quetz_theme-0.3.0.post1.data/data/share/jupyter/labextensions/quetz-theme/install.json
quetz_theme-0.3.0.post1.data/data/share/jupyter/labextensions/quetz-theme/package.json
quetz_theme-0.3.0.post1.data/data/share/jupyter/labextensions/quetz-theme/static/568.6ba9547c6360a2723636.js
quetz_theme-0.3.0.post1.data/data/share/jupyter/labextensions/quetz-theme/static/remoteEntry.b32b6c7ec2179a7bc5fc.js
quetz_theme-0.3.0.post1.data/data/share/jupyter/labextensions/quetz-theme/static/style.js
quetz_theme-0.3.0.post1.data/data/share/jupyter/labextensions/quetz-theme/static/third-party-licenses.json
quetz_theme-0.3.0.post1.data/data/share/jupyter/labextensions/quetz-theme/themes/quetz-theme/index.css
quetz_theme-0.3.0.post1.data/data/share/jupyter/labextensions/quetz-theme/themes/quetz-theme/index.js
quetz_theme-0.3.0.post1.dist-info/LICENSE
quetz_theme-0.3.0.post1.dist-info/METADATA
quetz_theme-0.3.0.post1.dist-info/WHEEL
quetz_theme-0.3.0.post1.dist-info/top_level.txt
quetz_theme-0.3.0.post1.dist-info/RECORD
